LICENSE
MANIFEST.in
README.rst
setup.py
sentry_unfuddle/__init__.py
sentry_unfuddle/__init__.pyc
sentry_unfuddle/forms.py
sentry_unfuddle/forms.pyc
sentry_unfuddle/models.py
sentry_unfuddle/models.pyc
sentry_unfuddle/plugin.py
sentry_unfuddle/plugin.pyc
sentry_unfuddle/unfuddle.py
sentry_unfuddle/unfuddle.pyc
sentry_unfuddle.egg-info/PKG-INFO
sentry_unfuddle.egg-info/SOURCES.txt
sentry_unfuddle.egg-info/dependency_links.txt
sentry_unfuddle.egg-info/entry_points.txt
sentry_unfuddle.egg-info/not-zip-safe
sentry_unfuddle.egg-info/requires.txt
sentry_unfuddle.egg-info/top_level.txt
sentry_unfuddle/templates/sentry_unfuddle/create_unfuddle_issue.html
sentry_unfuddle/templates/sentry_unfuddle/project_conf_form.html