Metadata-Version: 1.1
Name: sentry-unfuddle
Version: 1.0.1
Summary: A Sentry extension which creates Unfuddle issues from sentry events.
Home-page: http://github.com/rkeilty/sentry-unfuddle
Author: Rick Keilty
Author-email: rkeilty@gmail.com
License: BSD
Platform: UNKNOWN
Classifier: Intended Audience :: Developers
Classifier: Intended Audience :: System Administrators
Classifier: Operating System :: OS Independent
Classifier: License :: OSI Approved :: BSD License
Classifier: Programming Language :: Python
Classifier: Framework :: Django
Classifier: Topic :: Software Development
